dataclassabc/__init__.py
dataclassabc/py.typed
dataclassabc-0.0.18.dist-info/METADATA
dataclassabc-0.0.18.dist-info/WHEEL
dataclassabc-0.0.18.dist-info/licenses/LICENSE
dataclassabc-0.0.18.dist-info/RECORD
