Metadata-Version: 2.4
Name: dataclassabc
Version: 0.0.18
Summary: A Python library that allows you to define abstract properties for dataclasses, bridging the gap between abstract base classes (ABCs) and dataclasses.
Project-URL: Homepage, https://github.com/MichaelSchneeberger/dataclass-abc
Author-email: Michael Schneeberger <michael.schneeb@hotmail.com>
License-File: LICENSE
Requires-Python: >=3.10
Requires-Dist: typing-extensions>=4.11.0
